cm_qdk/__init__.py
cm_qdk/main.py
cm_qdk/tests/__init__.py
cm_qdk/tests/main_test.py
cm_qdk-0.0.2.dist-info/LICENSE
cm_qdk-0.0.2.dist-info/METADATA
cm_qdk-0.0.2.dist-info/WHEEL
cm_qdk-0.0.2.dist-info/top_level.txt
cm_qdk-0.0.2.dist-info/RECORD
