Metadata-Version: 2.1
Name: cm-qdk
Version: 0.0.2
Author: PunchyArchy
Author-email: ksmdrmvscthny@gmail.com
License-File: LICENSE
Requires-Dist: qodex-dk
